sara_sdk/__init__.py
sara_sdk/error.py
sara_sdk/client/__init__.py
sara_sdk/client/requests.py
sara_sdk/common/__init__.py
sara_sdk/common/session.py
sara_sdk/core/__init__.py
sara_sdk/core/iam/__init__.py
sara_sdk/core/iam/actions.py
sara_sdk/core/iam/apps.py
sara_sdk/core/iam/clients.py
sara_sdk/core/iam/fleets.py
sara_sdk/core/iam/groups.py
sara_sdk/core/iam/policies.py
sara_sdk/core/iam/robots.py
sara_sdk/core/iam/services.py
sara_sdk/core/iam/users.py
sara_sdk/core/metrics/__init__.py
sara_sdk/core/metrics/metrics.py
sara_sdk/core/missions/__init__.py
sara_sdk/core/missions/missions.py
sara_sdk/core/missions/stages.py
sara_sdk/core/missions/steps.py
sara_sdk/core/missions/tags.py
sara_sdk/core/srs/__init__.py
sara_sdk/core/srs/activities.py
sara_sdk/core/srs/buckets.py
sara_sdk/core/srs/relationships.py
sara_sdk/core/telemetry/__init__.py
sara_sdk/core/telemetry/telemetry.py
sara_sdk/core/webhook/__init__.py
sara_sdk/core/webhook/endpoints.py
sara_sdk/core/webhook/events.py
sara_sdk/core/webhook/events_execution.py
sara_sdk/core/webhook/topics.py
sara_sdk/utils/__init__.py
sara_sdk/utils/enum.py
sara_sdk/utils/rest.py
sara_sdk/utils/url.py
sara_sdk-1.1.0.dist-info/LICENSE
sara_sdk-1.1.0.dist-info/METADATA
sara_sdk-1.1.0.dist-info/WHEEL
sara_sdk-1.1.0.dist-info/top_level.txt
sara_sdk-1.1.0.dist-info/RECORD
