Metadata-Version: 2.1
Name: sara-sdk
Version: 1.1.0
Summary: Synkar SARA REST API SDK
Home-page: 
Author: Synkar Autonomous
Author-email: Synkar Autonomous <synkar@synkar.com>
License: MIT License        
Project-URL: Homepage, https://github.com/Synkar/Sara-SDK-Python
Keywords: synkar,sara,python-sdk,sdk
Classifier: License :: OSI Approved :: MIT License
Classifier: Programming Language :: Python
Classifier: Programming Language :: Python :: 3
Requires-Python: >=3.8
License-File: LICENSE
Requires-Dist: python-dotenv (>=0.19.2)
Requires-Dist: requests (>=2.27.1)
Requires-Dist: urllib3 (>=1.26.9)
